{
"type": "FeatureCollection",
"name": "FORSYTH",
"crs": { "type": "name", "properties": { "name": "urn:ogc:def:crs:OGC:1.3:CRS84" } },
"features": [
{ "type": "Feature", "properties": { "address": "1201 SAWNEE DRIVE, CUMMING, GA, 30040", "county": "FORSYTH", "election": "05/19/2026 MAY 19, 2026 - GENERAL PRIMARY ELECTION", "lat": 34.223817, "lng": -84.139113, "name": "ELECTIONS AND VOTER REGISTRATION OFFICE", "schedule": "04/27/2026 - 05/01/2026 8:00 AM - 6:00 PM ( Advanced Polling Location )\n04/27/2026 - 05/01/2026 8:00 AM - 6:00 PM ( Dropbox Polling Location )\n05/02/2026 - 05/03/2026 8:00 AM - 5:00 PM ( Advanced Polling Location )\n05/02/2026 - 05/03/2026 8:00 AM - 5:00 PM ( Dropbox Polling Location )\n05/04/2026 - 05/08/2026 8:00 AM - 6:00 PM ( Advanced Polling Location )\n05/04/2026 - 05/08/2026 8:00 AM - 6:00 PM ( Dropbox Polling Location )\n05/09/2026 - 05/09/2026 8:00 AM - 5:00 PM ( Advanced Polling Location )\n05/09/2026 - 05/09/2026 8:00 AM - 5:00 PM ( Dropbox Polling Location )\n05/11/2026 - 05/15/2026 8:00 AM - 6:00 PM ( Advanced Polling Location )\n05/11/2026 - 05/15/2026 8:00 AM - 6:00 PM ( Dropbox Polling Location )" }, "geometry": { "type": "Point", "coordinates": [ -84.139113, 34.223817 ] } },
{ "type": "Feature", "properties": { "address": "5345 SETTINGDOWN RD, CUMMING, GA, 30041", "county": "FORSYTH", "election": "05/19/2026 MAY 19, 2026 - GENERAL PRIMARY ELECTION", "lat": 34.305279, "lng": -84.067578, "name": "HAMPTON PARK LIBRARY", "schedule": "05/04/2026 - 05/08/2026 8:00 AM - 6:00 PM ( Advanced Polling Location )\n05/09/2026 - 05/09/2026 8:00 AM - 5:00 PM ( Advanced Polling Location )\n05/11/2026 - 05/15/2026 8:00 AM - 6:00 PM ( Advanced Polling Location )" }, "geometry": { "type": "Point", "coordinates": [ -84.067578, 34.305279 ] } },
{ "type": "Feature", "properties": { "address": "5100 POST RD, CUMMING, GA, 30040", "county": "FORSYTH", "election": "05/19/2026 MAY 19, 2026 - GENERAL PRIMARY ELECTION", "lat": 34.20236, "lng": -84.21864, "name": "MIDWAY PARK COMMUNITY BUILDING", "schedule": "05/04/2026 - 05/08/2026 8:00 AM - 6:00 PM ( Advanced Polling Location )\n05/09/2026 - 05/09/2026 8:00 AM - 5:00 PM ( Advanced Polling Location )\n05/11/2026 - 05/15/2026 8:00 AM - 6:00 PM ( Advanced Polling Location )" }, "geometry": { "type": "Point", "coordinates": [ -84.21864, 34.20236 ] } },
{ "type": "Feature", "properties": { "address": "1950 SHARON RD, CUMMING, GA, 30041", "county": "FORSYTH", "election": "05/19/2026 MAY 19, 2026 - GENERAL PRIMARY ELECTION", "lat": 34.116751, "lng": -84.164237, "name": "SHARON SPRINGS PARK COMMUNITY BUILDING", "schedule": "05/04/2026 - 05/08/2026 8:00 AM - 6:00 PM ( Advanced Polling Location )\n05/09/2026 - 05/09/2026 8:00 AM - 5:00 PM ( Advanced Polling Location )\n05/11/2026 - 05/15/2026 8:00 AM - 6:00 PM ( Advanced Polling Location )" }, "geometry": { "type": "Point", "coordinates": [ -84.164237, 34.116751 ] } }
]
}
