{
"type": "FeatureCollection",
"name": "HANCOCK",
"crs": { "type": "name", "properties": { "name": "urn:ogc:def:crs:OGC:1.3:CRS84" } },
"features": [
{ "type": "Feature", "properties": { "address": "9091 EAST BROAD STREET, SPARTA, GA, 31087", "county": "HANCOCK", "election": "05/19/2026 MAY 19, 2026 - GENERAL PRIMARY ELECTION", "lat": 33.275829, "lng": -82.969857, "name": "HANCOCK BOER OFFICE", "schedule": "04/27/2026 - 05/02/2026 9:00 AM - 5:00 PM ( Dropbox Polling Location )\n05/04/2026 - 05/09/2026 9:00 AM - 5:00 PM ( Dropbox Polling Location )\n05/11/2026 - 05/15/2026 9:00 AM - 5:00 PM ( Dropbox Polling Location )" }, "geometry": { "type": "Point", "coordinates": [ -82.969857, 33.275829 ] } },
{ "type": "Feature", "properties": { "address": "12560 AUGUSTA HWY E, SPARTA, GA, 31087", "county": "HANCOCK", "election": "05/19/2026 MAY 19, 2026 - GENERAL PRIMARY ELECTION", "lat": 33.280089, "lng": -82.964399, "name": "YOUTH CENTER", "schedule": "04/27/2026 - 05/02/2026 9:00 AM - 5:00 PM ( Advanced Polling Location )\n05/04/2026 - 05/09/2026 9:00 AM - 5:00 PM ( Advanced Polling Location )\n05/11/2026 - 05/15/2026 9:00 AM - 5:00 PM ( Advanced Polling Location )" }, "geometry": { "type": "Point", "coordinates": [ -82.964399, 33.280089 ] } }
]
}
