{
"type": "FeatureCollection",
"name": "HOUSTON",
"crs": { "type": "name", "properties": { "name": "urn:ogc:def:crs:OGC:1.3:CRS84" } },
"features": [
{ "type": "Feature", "properties": { "address": "2030 KINGS CHAPEL RD, PERRY, GA, 31069", "county": "HOUSTON", "election": "05/19/2026 MAY 19, 2026 - GENERAL PRIMARY ELECTION", "lat": 32.465059, "lng": -83.700524, "name": "BOARD OF ELECTIONS", "schedule": "04/27/2026 - 05/01/2026 8:00 AM - 5:00 PM ( Advanced Polling Location )\n04/27/2026 - 05/01/2026 8:00 AM - 5:00 PM ( Dropbox Polling Location )\n05/02/2026 - 05/02/2026 9:00 AM - 5:00 PM ( Advanced Polling Location )\n05/02/2026 - 05/02/2026 9:00 AM - 5:00 PM ( Dropbox Polling Location )\n05/04/2026 - 05/08/2026 8:00 AM - 5:00 PM ( Advanced Polling Location )\n05/04/2026 - 05/08/2026 8:00 AM - 5:00 PM ( Dropbox Polling Location )\n05/09/2026 - 05/09/2026 9:00 AM - 5:00 PM ( Advanced Polling Location )\n05/09/2026 - 05/09/2026 9:00 AM - 5:00 PM ( Dropbox Polling Location )\n05/11/2026 - 05/15/2026 8:00 AM - 5:00 PM ( Advanced Polling Location )\n05/11/2026 - 05/15/2026 8:00 AM - 5:00 PM ( Dropbox Polling Location )" }, "geometry": { "type": "Point", "coordinates": [ -83.700524, 32.465059 ] } },
{ "type": "Feature", "properties": { "address": "71 COHEN WALKER DR, WARNER ROBINS, GA, 31088", "county": "HOUSTON", "election": "05/19/2026 MAY 19, 2026 - GENERAL PRIMARY ELECTION", "lat": 32.546135, "lng": -83.671474, "name": "CENTRAL GA TECH HEALTH SCIENCES BLDG", "schedule": "04/27/2026 - 05/01/2026 8:00 AM - 5:00 PM ( Advanced Polling Location )\n05/02/2026 - 05/02/2026 9:00 AM - 5:00 PM ( Advanced Polling Location )\n05/04/2026 - 05/08/2026 8:00 AM - 5:00 PM ( Advanced Polling Location )\n05/09/2026 - 05/09/2026 9:00 AM - 5:00 PM ( Advanced Polling Location )\n05/11/2026 - 05/15/2026 8:00 AM - 5:00 PM ( Advanced Polling Location )" }, "geometry": { "type": "Point", "coordinates": [ -83.671474, 32.546135 ] } },
{ "type": "Feature", "properties": { "address": "233 N HOUSTON RD, WARNER ROBINS, GA, 31093", "county": "HOUSTON", "election": "05/19/2026 MAY 19, 2026 - GENERAL PRIMARY ELECTION", "lat": 32.620161, "lng": -83.643382, "name": "HOUSTON HEALTH PAVILION CONF CENTER", "schedule": "04/27/2026 - 05/01/2026 8:00 AM - 5:00 PM ( Advanced Polling Location )\n04/27/2026 - 05/01/2026 8:00 AM - 5:00 PM ( Dropbox Polling Location )\n05/02/2026 - 05/02/2026 9:00 AM - 5:00 PM ( Advanced Polling Location )\n05/02/2026 - 05/02/2026 9:00 AM - 5:00 PM ( Dropbox Polling Location )\n05/04/2026 - 05/08/2026 8:00 AM - 5:00 PM ( Advanced Polling Location )\n05/04/2026 - 05/08/2026 8:00 AM - 5:00 PM ( Dropbox Polling Location )\n05/09/2026 - 05/09/2026 9:00 AM - 5:00 PM ( Advanced Polling Location )\n05/09/2026 - 05/09/2026 9:00 AM - 5:00 PM ( Dropbox Polling Location )\n05/11/2026 - 05/15/2026 8:00 AM - 5:00 PM ( Advanced Polling Location )\n05/11/2026 - 05/15/2026 8:00 AM - 5:00 PM ( Dropbox Polling Location )" }, "geometry": { "type": "Point", "coordinates": [ -83.643382, 32.620161 ] } },
{ "type": "Feature", "properties": { "address": "900 N HOUSTON RD, WARNER ROBINS, GA, 31093", "county": "HOUSTON", "election": "05/19/2026 MAY 19, 2026 - GENERAL PRIMARY ELECTION", "lat": 32.636525, "lng": -83.638907, "name": "NORTH HOUSTON SPORTS COMPLEX", "schedule": "04/27/2026 - 05/01/2026 8:00 AM - 5:00 PM ( Advanced Polling Location )\n05/02/2026 - 05/02/2026 9:00 AM - 5:00 PM ( Advanced Polling Location )\n05/04/2026 - 05/08/2026 8:00 AM - 5:00 PM ( Advanced Polling Location )\n05/09/2026 - 05/09/2026 9:00 AM - 5:00 PM ( Advanced Polling Location )\n05/11/2026 - 05/15/2026 8:00 AM - 5:00 PM ( Advanced Polling Location )" }, "geometry": { "type": "Point", "coordinates": [ -83.638907, 32.636525 ] } }
]
}
