{
"type": "FeatureCollection",
"name": "NEWTON",
"crs": { "type": "name", "properties": { "name": "urn:ogc:def:crs:OGC:1.3:CRS84" } },
"features": [
{ "type": "Feature", "properties": { "address": "6752 HIGHWAY 212, COVINGTON, GA, 30016", "county": "NEWTON", "election": "05/19/2026 MAY 19, 2026 - GENERAL PRIMARY ELECTION", "lat": 33.540176, "lng": -84.009455, "name": "PROSPECT CHURCH AT OAK HILL", "schedule": "04/27/2026 - 05/01/2026 8:00 AM - 5:00 PM ( Advanced Polling Location )\n05/04/2026 - 05/08/2026 8:00 AM - 5:00 PM ( Advanced Polling Location )\n05/11/2026 - 05/15/2026 8:00 AM - 5:00 PM ( Advanced Polling Location )" }, "geometry": { "type": "Point", "coordinates": [ -84.009455, 33.540176 ] } },
{ "type": "Feature", "properties": { "address": "6185 TURNER LAKE RD NW, COVINGTON, GA, 30014", "county": "NEWTON", "election": "05/19/2026 MAY 19, 2026 - GENERAL PRIMARY ELECTION", "lat": 33.600283, "lng": -83.879598, "name": "TURNER LAKE RECREATION CENTER - BANQUET RM", "schedule": "04/27/2026 - 05/01/2026 8:00 AM - 5:00 PM ( Advanced Polling Location )\n05/02/2026 - 05/02/2026 9:00 AM - 5:00 PM ( Advanced Polling Location )\n05/04/2026 - 05/08/2026 8:00 AM - 5:00 PM ( Advanced Polling Location )\n05/09/2026 - 05/09/2026 9:00 AM - 5:00 PM ( Advanced Polling Location )\n05/11/2026 - 05/12/2026 8:00 AM - 5:00 PM ( Advanced Polling Location )\n05/13/2026 - 05/13/2026 8:00 AM - 7:00 PM ( Advanced Polling Location )\n05/14/2026 - 05/14/2026 8:00 AM - 7:00 PM ( Advanced Polling Location )\n05/15/2026 - 05/15/2026 8:00 AM - 7:00 PM ( Advanced Polling Location )" }, "geometry": { "type": "Point", "coordinates": [ -83.879598, 33.600283 ] } }
]
}
