{
"type": "FeatureCollection",
"name": "QUITMAN",
"crs": { "type": "name", "properties": { "name": "urn:ogc:def:crs:OGC:1.3:CRS84" } },
"features": [
{ "type": "Feature", "properties": { "address": "37 OLD SCHOOL ROAD, GEORGETOWN, GA, 39854", "county": "QUITMAN", "election": "05/19/2026 MAY 19, 2026 - GENERAL PRIMARY ELECTION", "lat": 31.885339, "lng": -85.100179, "name": "GEORGETOWN PRECINCT", "schedule": "04/27/2026 - 05/01/2026 9:00 AM - 5:00 PM ( Advanced Polling Location )\n04/27/2026 - 05/01/2026 9:00 AM - 5:00 PM ( Dropbox Polling Location )\n05/02/2026 - 05/02/2026 9:00 AM - 5:00 PM ( Advanced Polling Location )\n05/02/2026 - 05/02/2026 9:00 AM - 5:00 PM ( Dropbox Polling Location )\n05/04/2026 - 05/08/2026 9:00 AM - 5:00 PM ( Advanced Polling Location )\n05/04/2026 - 05/08/2026 9:00 AM - 5:00 PM ( Dropbox Polling Location )\n05/09/2026 - 05/09/2026 9:00 AM - 5:00 PM ( Advanced Polling Location )\n05/09/2026 - 05/09/2026 9:00 AM - 5:00 PM ( Dropbox Polling Location )\n05/11/2026 - 05/15/2026 9:00 AM - 5:00 PM ( Advanced Polling Location )\n05/11/2026 - 05/15/2026 9:00 AM - 5:00 PM ( Dropbox Polling Location )" }, "geometry": { "type": "Point", "coordinates": [ -85.100179, 31.885339 ] } }
]
}
