{
"type": "FeatureCollection",
"name": "RANDOLPH",
"crs": { "type": "name", "properties": { "name": "urn:ogc:def:crs:OGC:1.3:CRS84" } },
"features": [
{ "type": "Feature", "properties": { "address": "93 FRONT ST, CUTHBERT, GA, 39840", "county": "RANDOLPH", "election": "05/19/2026 MAY 19, 2026 - GENERAL PRIMARY ELECTION", "lat": 31.76671, "lng": -84.786887, "name": "COURTHOUSE-GOVT CENTER", "schedule": "04/27/2026 - 05/02/2026 8:00 AM - 5:00 PM ( Advanced Polling Location )\n04/27/2026 - 05/02/2026 8:00 AM - 5:00 PM ( Dropbox Polling Location )\n05/04/2026 - 05/09/2026 8:00 AM - 5:00 PM ( Advanced Polling Location )\n05/04/2026 - 05/09/2026 8:00 AM - 5:00 PM ( Dropbox Polling Location )\n05/11/2026 - 05/15/2026 8:00 AM - 5:00 PM ( Advanced Polling Location )\n05/11/2026 - 05/15/2026 8:00 AM - 5:00 PM ( Dropbox Polling Location )" }, "geometry": { "type": "Point", "coordinates": [ -84.786887, 31.76671 ] } }
]
}
