{
"type": "FeatureCollection",
"name": "WHEELER",
"crs": { "type": "name", "properties": { "name": "urn:ogc:def:crs:OGC:1.3:CRS84" } },
"features": [
{ "type": "Feature", "properties": { "address": "16 W FOREST AVE, ALAMO, GA, 30411", "county": "WHEELER", "election": "05/19/2026 MAY 19, 2026 - GENERAL PRIMARY ELECTION", "lat": 32.148696, "lng": -82.782944, "name": "COMMUNITY SERVICE CENTER", "schedule": "04/27/2026 - 05/02/2026 9:00 AM - 5:00 PM ( Advanced Polling Location )\n04/27/2026 - 05/02/2026 9:00 AM - 5:00 PM ( Dropbox Polling Location )\n05/04/2026 - 05/09/2026 9:00 AM - 5:00 PM ( Advanced Polling Location )\n05/04/2026 - 05/09/2026 9:00 AM - 5:00 PM ( Dropbox Polling Location )\n05/11/2026 - 05/15/2026 9:00 AM - 5:00 PM ( Advanced Polling Location )\n05/11/2026 - 05/15/2026 9:00 AM - 5:00 PM ( Dropbox Polling Location )\n05/18/2026 - 05/18/2026 9:00 AM - 5:00 PM ( Dropbox Polling Location )\n05/19/2026 - 05/19/2026 9:00 AM - 5:00 PM ( Dropbox Polling Location )" }, "geometry": { "type": "Point", "coordinates": [ -82.782944, 32.148696 ] } }
]
}
