{
"type": "FeatureCollection",
"name": "errors",
"crs": { "type": "name", "properties": { "name": "urn:ogc:def:crs:OGC:1.3:CRS84" } },
"features": [
{ "type": "Feature", "properties": { "address": "25 COURT SQUARE, HOMERVILLE, GA, 31634", "county": "CLINCH", "election": "11/04/2025 NOVEMBER 4, 2025 - MUNICIPAL GENERAL / SPECIAL ELECTION (PSC)", "lat": 33.801362, "lng": -85.189737, "name": "COURTHOUSE", "schedule": "10/20/2025 - 10/24/2025 9:00 AM - 5:00 PM ( Advanced Polling Location )\n10/27/2025 - 10/31/2025 9:00 AM - 5:00 PM ( Advanced Polling Location )\n10/27/2025 - 10/31/2025 9:00 AM - 5:00 PM ( Dropbox Polling Location )" }, "geometry": { "type": "Point", "coordinates": [ -85.189737, 33.801362 ] } }
]
}
