{
"type": "FeatureCollection",
"name": "BRANTLEY",
"crs": { "type": "name", "properties": { "name": "urn:ogc:def:crs:OGC:1.3:CRS84" } },
"features": [
{ "type": "Feature", "properties": { "address": "10305 MAIN ST, NAHUNTA, GA, 31553", "county": "BRANTLEY", "election": "11/05/2024 NOVEMBER 5, 2024 - GENERAL ELECTION", "lat": 31.210055, "lng": -81.980552, "name": "BRANTLEY CO. ELECTIONS", "schedule": "10/15/2024 - 10/19/2024 8:00 AM - 5:00 PM\n10/21/2024 - 10/26/2024 8:00 AM - 5:00 PM\n10/28/2024 - 11/01/2024 8:00 AM - 5:00 PM\n11/04/2024 - 11/04/2024 8:00 AM - 5:00 PM" }, "geometry": { "type": "Point", "coordinates": [ -81.980552, 31.210055 ] } }
]
}
