{
"type": "FeatureCollection",
"name": "JACKSON",
"crs": { "type": "name", "properties": { "name": "urn:ogc:def:crs:OGC:1.3:CRS84" } },
"features": [
{ "type": "Feature", "properties": { "address": "441 Gordon Street, Jefferson, GA, 30549", "county": "JACKSON", "election": "11/05/2024 NOVEMBER 5, 2024 - GENERAL ELECTION", "lat": 34.112275, "lng": -83.568364, "name": "ELECTION OFFICE", "schedule": "10/15/2024 - 10/19/2024 9:00 AM - 5:00 PM\n10/15/2024 - 10/19/2024 9:00 AM - 5:00 PM\n10/21/2024 - 10/26/2024 9:00 AM - 5:00 PM\n10/21/2024 - 10/26/2024 9:00 AM - 5:00 PM\n10/28/2024 - 11/01/2024 9:00 AM - 5:00 PM\n10/28/2024 - 11/01/2024 9:00 AM - 5:00 PM" }, "geometry": { "type": "Point", "coordinates": [ -83.568364, 34.112275 ] } },
{ "type": "Feature", "properties": { "address": "1345 S ELM ST, COMMERCE, GA, 30529 0000", "county": "JACKSON", "election": "11/05/2024 NOVEMBER 5, 2024 - GENERAL ELECTION", "lat": 34.198507, "lng": -83.453901, "name": "FBC COMMERCE", "schedule": "10/28/2024 - 11/01/2024 9:00 AM - 5:00 PM" }, "geometry": { "type": "Point", "coordinates": [ -83.453901, 34.198507 ] } },
{ "type": "Feature", "properties": { "address": "5040 HIGHWAY 53, BRASELTON, GA, 30517 0000", "county": "JACKSON", "election": "11/05/2024 NOVEMBER 5, 2024 - GENERAL ELECTION", "lat": 34.1078, "lng": -83.762161, "name": "POLICE & MUNICIPAL COURT BLDG", "schedule": "10/28/2024 - 11/01/2024 9:00 AM - 5:00 PM" }, "geometry": { "type": "Point", "coordinates": [ -83.762161, 34.1078 ] } }
]
}
