{
"type": "FeatureCollection",
"name": "JASPER",
"crs": { "type": "name", "properties": { "name": "urn:ogc:def:crs:OGC:1.3:CRS84" } },
"features": [
{ "type": "Feature", "properties": { "address": "126 WEST GREENE STREET SUITE 3, MONTICELLO, GA, 31064 0000", "county": "JASPER", "election": "11/05/2024 NOVEMBER 5, 2024 - GENERAL ELECTION", "lat": 33.304924, "lng": -83.683597, "name": "JASPER COUNTY COURTHOUSE", "schedule": "10/15/2024 - 10/19/2024 9:00 AM - 5:00 PM\n10/21/2024 - 10/26/2024 9:00 AM - 5:00 PM\n10/28/2024 - 11/01/2024 9:00 AM - 5:00 PM" }, "geometry": { "type": "Point", "coordinates": [ -83.683597, 33.304924 ] } }
]
}
