{
"type": "FeatureCollection",
"name": "LIBERTY",
"crs": { "type": "name", "properties": { "name": "urn:ogc:def:crs:OGC:1.3:CRS84" } },
"features": [
{ "type": "Feature", "properties": { "address": "9397 E. OGLETHORPE HWY., MIDWAY, GA, 31320 0000", "county": "LIBERTY", "election": "11/05/2024 NOVEMBER 5, 2024 - GENERAL ELECTION", "lat": 31.798179, "lng": -81.45454, "name": "LIBERTY COUNTY COMPLEX", "schedule": "10/15/2024 - 10/19/2024 9:00 AM - 5:00 PM\n10/21/2024 - 10/26/2024 9:00 AM - 5:00 PM\n10/28/2024 - 11/01/2024 9:00 AM - 5:00 PM" }, "geometry": { "type": "Point", "coordinates": [ -81.45454, 31.798179 ] } },
{ "type": "Feature", "properties": { "address": "100 N. MAIN ST .SUITE 1600, HINESVILLE, GA, 31313", "county": "LIBERTY", "election": "11/05/2024 NOVEMBER 5, 2024 - GENERAL ELECTION", "lat": 31.847679, "lng": -81.59582, "name": "MAIN OFFICE", "schedule": "10/15/2024 - 10/19/2024 9:00 AM - 5:00 PM\n10/21/2024 - 10/26/2024 9:00 AM - 5:00 PM\n10/28/2024 - 11/01/2024 9:00 AM - 5:00 PM" }, "geometry": { "type": "Point", "coordinates": [ -81.59582, 31.847679 ] } }
]
}
