{
"type": "FeatureCollection",
"name": "MERIWETHER",
"crs": { "type": "name", "properties": { "name": "urn:ogc:def:crs:OGC:1.3:CRS84" } },
"features": [
{ "type": "Feature", "properties": { "address": "137 s. court square, greenville, GA, 30222", "county": "MERIWETHER", "election": "11/05/2024 NOVEMBER 5, 2024 - GENERAL ELECTION", "lat": 33.028063, "lng": -84.713006, "name": "ELECTION HQ", "schedule": "10/15/2024 - 10/18/2024 8:30 AM - 5:00 PM\n10/15/2024 - 10/18/2024 8:30 AM - 5:00 PM\n10/19/2024 - 10/19/2024 9:00 AM - 5:00 PM\n10/19/2024 - 10/19/2024 9:00 AM - 5:00 PM\n10/21/2024 - 10/25/2024 8:30 AM - 5:00 PM\n10/21/2024 - 10/25/2024 8:30 AM - 5:00 PM\n10/26/2024 - 10/26/2024 9:00 AM - 5:00 PM\n10/26/2024 - 10/26/2024 9:00 AM - 5:00 PM\n10/28/2024 - 11/01/2024 8:30 AM - 5:00 PM\n10/28/2024 - 11/01/2024 8:30 AM - 5:00 PM" }, "geometry": { "type": "Point", "coordinates": [ -84.713006, 33.028063 ] } }
]
}
