{
"type": "FeatureCollection",
"name": "MORGAN",
"crs": { "type": "name", "properties": { "name": "urn:ogc:def:crs:OGC:1.3:CRS84" } },
"features": [
{ "type": "Feature", "properties": { "address": "237 N 2ND ST, MADISON, GA, 30650", "county": "MORGAN", "election": "11/05/2024 NOVEMBER 5, 2024 - GENERAL ELECTION", "lat": 33.59903, "lng": -83.46688, "name": "ABSA", "schedule": "10/15/2024 - 10/18/2024 8:00 AM - 5:00 PM\n10/19/2024 - 10/19/2024 9:00 AM - 5:00 PM\n10/21/2024 - 10/25/2024 8:00 AM - 5:00 PM\n10/26/2024 - 10/26/2024 9:00 AM - 5:00 PM\n10/28/2024 - 11/01/2024 8:00 AM - 5:00 PM" }, "geometry": { "type": "Point", "coordinates": [ -83.46688, 33.59903 ] } }
]
}
