{
"type": "FeatureCollection",
"name": "SPALDING",
"crs": { "type": "name", "properties": { "name": "urn:ogc:def:crs:OGC:1.3:CRS84" } },
"features": [
{ "type": "Feature", "properties": { "address": "825 MEMORIAL DR, GRIFFIN, GA, 30223", "county": "SPALDING", "election": "11/05/2024 NOVEMBER 5, 2024 - GENERAL ELECTION", "lat": 33.24691, "lng": -84.25516, "name": "SPALDING COUNTY ELECTIONS AND VOTER REGISTRATION", "schedule": "10/15/2024 - 10/19/2024 8:00 AM - 6:00 PM\n10/15/2024 - 10/19/2024 8:00 AM - 6:00 PM\n10/21/2024 - 10/26/2024 8:00 AM - 6:00 PM\n10/21/2024 - 10/26/2024 8:00 AM - 6:00 PM\n10/28/2024 - 11/01/2024 8:00 AM - 6:00 PM\n10/28/2024 - 11/01/2024 8:00 AM - 6:00 PM" }, "geometry": { "type": "Point", "coordinates": [ -84.25516, 33.24691 ] } }
]
}
