{
"type": "FeatureCollection",
"name": "BAKER",
"crs": { "type": "name", "properties": { "name": "urn:ogc:def:crs:OGC:1.3:CRS84" } },
"features": [
{ "type": "Feature", "properties": { "address": "167 BAKER PLACE, NEWTON, GA, 39870", "county": "BAKER", "election": "11/04/2025 NOVEMBER 4, 2025 - MUNICIPAL GENERAL / SPECIAL ELECTION (PSC)", "lat": 31.317846, "lng": -84.342274, "name": "BAKER COUNTY COURTHOUSE", "schedule": "10/14/2025 - 10/25/2025 9:00 AM - 5:00 PM ( Advanced Polling Location )\n10/27/2025 - 10/31/2025 9:00 AM - 5:00 PM ( Advanced Polling Location )\n10/14/2025 - 10/25/2025 9:00 AM - 5:00 PM ( Dropbox Polling Location )\n10/27/2025 - 10/31/2025 9:00 AM - 5:00 PM ( Dropbox Polling Location )" }, "geometry": { "type": "Point", "coordinates": [ -84.342274, 31.317846 ] } }
]
}
