{
"type": "FeatureCollection",
"name": "BARROW",
"crs": { "type": "name", "properties": { "name": "urn:ogc:def:crs:OGC:1.3:CRS84" } },
"features": [
{ "type": "Feature", "properties": { "address": "233 E. BROAD ST, WINDER, GA, 30680", "county": "BARROW", "election": "11/04/2025 NOVEMBER 4, 2025 - MUNICIPAL GENERAL / SPECIAL ELECTION (PSC)", "lat": 33.997723, "lng": -83.709377, "name": "BARROW COUNTY ELECTIONS OFFICE", "schedule": "10/20/2025 - 10/24/2025 8:00 AM - 5:00 PM ( Advanced Polling Location )\n10/25/2025 - 10/25/2025 9:00 AM - 5:00 PM ( Advanced Polling Location )\n10/27/2025 - 10/31/2025 8:00 AM - 5:00 PM ( Advanced Polling Location )\n10/20/2025 - 10/24/2025 8:00 AM - 5:00 PM ( Dropbox Polling Location )\n10/25/2025 - 10/25/2025 9:00 AM - 5:00 PM ( Dropbox Polling Location )\n10/27/2025 - 10/31/2025 8:00 AM - 5:00 PM ( Dropbox Polling Location )" }, "geometry": { "type": "Point", "coordinates": [ -83.709377, 33.997723 ] } }
]
}
