{
"type": "FeatureCollection",
"name": "CLARKE",
"crs": { "type": "name", "properties": { "name": "urn:ogc:def:crs:OGC:1.3:CRS84" } },
"features": [
{ "type": "Feature", "properties": { "address": "2025 BAXTER STREET, ATHENS, GA, 30606", "county": "CLARKE", "election": "11/04/2025 NOVEMBER 4, 2025 - MUNICIPAL GENERAL / SPECIAL ELECTION (PSC)", "lat": 33.944951, "lng": -83.403645, "name": "ATHENS REGIONAL LIBRARY", "schedule": "10/25/2025 - 10/25/2025 9:00 AM - 4:00 PM ( Advanced Polling Location )\n10/27/2025 - 10/27/2025 8:00 AM - 5:00 PM ( Advanced Polling Location )\n10/28/2025 - 10/28/2025 8:00 AM - 5:00 PM ( Advanced Polling Location )\n10/29/2025 - 10/29/2025 8:00 AM - 5:00 PM ( Advanced Polling Location )\n10/30/2025 - 10/30/2025 8:00 AM - 5:00 PM ( Advanced Polling Location )\n10/31/2025 - 10/31/2025 8:00 AM - 5:00 PM ( Advanced Polling Location )" }, "geometry": { "type": "Point", "coordinates": [ -83.403645, 33.944951 ] } },
{ "type": "Feature", "properties": { "address": "4460 LEXINGTON RD, ATHENS, GA, 30605", "county": "CLARKE", "election": "11/04/2025 NOVEMBER 4, 2025 - MUNICIPAL GENERAL / SPECIAL ELECTION (PSC)", "lat": 33.925351, "lng": -83.303055, "name": "ATHENS-CLARKE COUNTY TENNIS CENTER", "schedule": "10/25/2025 - 10/25/2025 9:00 AM - 4:00 PM ( Advanced Polling Location )\n10/27/2025 - 10/27/2025 8:00 AM - 5:00 PM ( Advanced Polling Location )\n10/28/2025 - 10/28/2025 8:00 AM - 5:00 PM ( Advanced Polling Location )\n10/29/2025 - 10/29/2025 8:00 AM - 5:00 PM ( Advanced Polling Location )\n10/30/2025 - 10/30/2025 8:00 AM - 5:00 PM ( Advanced Polling Location )\n10/31/2025 - 10/31/2025 8:00 AM - 5:00 PM ( Advanced Polling Location )" }, "geometry": { "type": "Point", "coordinates": [ -83.303055, 33.925351 ] } },
{ "type": "Feature", "properties": { "address": "155 E. WASHINGTON STREET, ATHENS, GA, 30601", "county": "CLARKE", "election": "11/04/2025 NOVEMBER 4, 2025 - MUNICIPAL GENERAL / SPECIAL ELECTION (PSC)", "lat": 33.959388, "lng": -83.376722, "name": "ELECTIONS OFFICE", "schedule": "10/31/2025 - 10/31/2025 8:00 AM - 5:00 PM ( Advanced Polling Location )\n10/22/2025 - 10/22/2025 8:00 AM - 5:00 PM ( Advanced Polling Location )\n10/23/2025 - 10/23/2025 8:00 AM - 5:00 PM ( Advanced Polling Location )\n10/24/2025 - 10/24/2025 8:00 AM - 5:00 PM ( Advanced Polling Location )\n10/25/2025 - 10/25/2025 9:00 AM - 4:00 PM ( Advanced Polling Location )\n10/27/2025 - 10/27/2025 8:00 AM - 5:00 PM ( Advanced Polling Location )\n10/28/2025 - 10/28/2025 8:00 AM - 5:00 PM ( Advanced Polling Location )\n10/29/2025 - 10/29/2025 8:00 AM - 5:00 PM ( Advanced Polling Location )\n10/30/2025 - 10/30/2025 8:00 AM - 5:00 PM ( Advanced Polling Location )\n10/30/2025 - 10/30/2025 8:00 AM - 5:00 PM ( Dropbox Polling Location )\n10/28/2025 - 10/28/2025 8:00 AM - 5:00 PM ( Dropbox Polling Location )\n10/23/2025 - 10/23/2025 8:00 AM - 5:00 PM ( Dropbox Polling Location )\n10/22/2025 - 10/22/2025 8:00 AM - 5:00 PM ( Dropbox Polling Location )\n10/24/2025 - 10/24/2025 8:00 AM - 5:00 PM ( Dropbox Polling Location )\n10/29/2025 - 10/29/2025 8:00 AM - 5:00 PM ( Dropbox Polling Location )\n10/25/2025 - 10/25/2025 9:00 AM - 4:00 PM ( Dropbox Polling Location )\n10/31/2025 - 10/31/2025 8:00 AM - 5:00 PM ( Dropbox Polling Location )\n10/27/2025 - 10/27/2025 8:00 AM - 5:00 PM ( Dropbox Polling Location )" }, "geometry": { "type": "Point", "coordinates": [ -83.376722, 33.959388 ] } }
]
}
