{
"type": "FeatureCollection",
"name": "DOOLY",
"crs": { "type": "name", "properties": { "name": "urn:ogc:def:crs:OGC:1.3:CRS84" } },
"features": [
{ "type": "Feature", "properties": { "address": "563 RAILROAD STREET, UNADILLA, GA, 31091 0000", "county": "DOOLY", "election": "11/04/2025 NOVEMBER 4, 2025 - MUNICIPAL GENERAL / SPECIAL ELECTION (PSC)", "lat": 32.263119, "lng": -83.735373, "name": "UNADILLA VOTING PRECINCT", "schedule": "10/20/2025 - 10/25/2025 8:00 AM - 5:00 PM ( Advanced Polling Location )\n10/27/2025 - 10/31/2025 8:00 AM - 5:00 PM ( Advanced Polling Location )" }, "geometry": { "type": "Point", "coordinates": [ -83.735373, 32.263119 ] } },
{ "type": "Feature", "properties": { "address": "402 HAWKINSVILLE ROAD, VIENNA, GA, 31092", "county": "DOOLY", "election": "11/04/2025 NOVEMBER 4, 2025 - MUNICIPAL GENERAL / SPECIAL ELECTION (PSC)", "lat": 32.095849, "lng": -83.780119, "name": "VIENNA VOTING PRECINCT", "schedule": "10/20/2025 - 10/25/2025 8:00 AM - 5:00 PM ( Advanced Polling Location )\n10/27/2025 - 10/31/2025 8:00 AM - 5:00 PM ( Advanced Polling Location )\n10/14/2025 - 10/27/2025 8:00 AM - 5:00 PM ( Dropbox Polling Location )\n10/28/2025 - 11/03/2025 8:00 AM - 5:00 PM ( Dropbox Polling Location )" }, "geometry": { "type": "Point", "coordinates": [ -83.780119, 32.095849 ] } }
]
}
