{
"type": "FeatureCollection",
"name": "EFFINGHAM",
"crs": { "type": "name", "properties": { "name": "urn:ogc:def:crs:OGC:1.3:CRS84" } },
"features": [
{ "type": "Feature", "properties": { "address": "284 GA HIGHWAY 119 S., SPRINGFIELD, GA, 31329", "county": "EFFINGHAM", "election": "11/04/2025 NOVEMBER 4, 2025 - MUNICIPAL GENERAL / SPECIAL ELECTION (PSC)", "lat": 32.3684, "lng": -81.31673, "name": "EFFINGHAM CO. BOARD OF ELECTIONS AND REGISTRATION", "schedule": "10/20/2025 - 10/25/2025 9:00 AM - 5:00 PM ( Advanced Polling Location )\n10/27/2025 - 10/31/2025 9:00 AM - 5:00 PM ( Advanced Polling Location )\n10/14/2025 - 10/27/2025 9:00 AM - 5:00 PM ( Dropbox Polling Location )\n10/28/2025 - 10/31/2025 9:00 AM - 5:00 PM ( Dropbox Polling Location )" }, "geometry": { "type": "Point", "coordinates": [ -81.31673, 32.3684 ] } }
]
}
