{
"type": "FeatureCollection",
"name": "HOUSTON",
"crs": { "type": "name", "properties": { "name": "urn:ogc:def:crs:OGC:1.3:CRS84" } },
"features": [
{ "type": "Feature", "properties": { "address": "2030 KINGS CHAPEL RD, PERRY, GA, 31069", "county": "HOUSTON", "election": "11/04/2025 NOVEMBER 4, 2025 - MUNICIPAL GENERAL / SPECIAL ELECTION (PSC)", "lat": 32.464959, "lng": -83.701818, "name": "BOARD OF ELECTIONS", "schedule": "10/20/2025 - 10/24/2025 8:00 AM - 5:00 PM ( Advanced Polling Location )\n10/25/2025 - 10/25/2025 9:00 AM - 5:00 PM ( Advanced Polling Location )\n10/27/2025 - 10/31/2025 8:00 AM - 5:00 PM ( Advanced Polling Location )\n10/20/2025 - 10/24/2025 8:00 AM - 5:00 PM ( Dropbox Polling Location )\n10/25/2025 - 10/25/2025 9:00 AM - 5:00 PM ( Dropbox Polling Location )\n10/27/2025 - 10/31/2025 8:00 AM - 5:00 PM ( Dropbox Polling Location )" }, "geometry": { "type": "Point", "coordinates": [ -83.701818, 32.464959 ] } },
{ "type": "Feature", "properties": { "address": "233 N HOUSTON RD, WARNER ROBINS, GA, 31093", "county": "HOUSTON", "election": "11/04/2025 NOVEMBER 4, 2025 - MUNICIPAL GENERAL / SPECIAL ELECTION (PSC)", "lat": 32.621859, "lng": -83.642371, "name": "HOUSTON HEALTH PAVILION CONF CENTER", "schedule": "10/27/2025 - 10/31/2025 8:00 AM - 5:00 PM ( Advanced Polling Location )\n10/20/2025 - 10/24/2025 8:00 AM - 5:00 PM ( Advanced Polling Location )\n10/25/2025 - 10/25/2025 9:00 AM - 5:00 PM ( Advanced Polling Location )\n10/20/2025 - 10/24/2025 8:00 AM - 5:00 PM ( Dropbox Polling Location )\n10/27/2025 - 10/31/2025 8:00 AM - 5:00 PM ( Dropbox Polling Location )\n10/25/2025 - 10/25/2025 9:00 AM - 5:00 PM ( Dropbox Polling Location )" }, "geometry": { "type": "Point", "coordinates": [ -83.642371, 32.621859 ] } }
]
}
