{
"type": "FeatureCollection",
"name": "JEFFERSON",
"crs": { "type": "name", "properties": { "name": "urn:ogc:def:crs:OGC:1.3:CRS84" } },
"features": [
{ "type": "Feature", "properties": { "address": "1200 SCHOOL STREET, LOUISVILLE, GA, 30434", "county": "JEFFERSON", "election": "11/04/2025 NOVEMBER 4, 2025 - MUNICIPAL GENERAL / SPECIAL ELECTION (PSC)", "lat": 33.00994, "lng": -82.394092, "name": "BOARD OF ELECTIONS", "schedule": "10/27/2025 - 10/31/2025 9:00 AM - 5:00 PM ( Advanced Polling Location )\n10/20/2025 - 10/25/2025 9:00 AM - 5:00 PM ( Advanced Polling Location )\n10/27/2025 - 10/31/2025 9:00 AM - 5:00 PM ( Dropbox Polling Location )\n10/20/2025 - 10/25/2025 9:00 AM - 5:00 PM ( Dropbox Polling Location )" }, "geometry": { "type": "Point", "coordinates": [ -82.394092, 33.00994 ] } },
{ "type": "Feature", "properties": { "address": "1200 SCHOOL STREET, LOUISVILLE, GA, 30434 0000", "county": "JEFFERSON", "election": "11/04/2025 NOVEMBER 4, 2025 - MUNICIPAL GENERAL / SPECIAL ELECTION (PSC)", "lat": 33.00994, "lng": -82.394092, "name": "JEFFERSON COUNTY BOARD OF ELECTIONS AND REGISTRATION", "schedule": "10/20/2025 - 10/25/2025 9:00 AM - 5:00 PM ( Advanced Polling Location )\n10/27/2025 - 10/31/2025 9:00 AM - 5:00 PM ( Advanced Polling Location )\n10/14/2025 - 10/27/2025 9:00 AM - 5:00 PM ( Dropbox Polling Location )" }, "geometry": { "type": "Point", "coordinates": [ -82.394092, 33.00994 ] } }
]
}
