{
"type": "FeatureCollection",
"name": "LANIER",
"crs": { "type": "name", "properties": { "name": "urn:ogc:def:crs:OGC:1.3:CRS84" } },
"features": [
{ "type": "Feature", "properties": { "address": "162 W THIGPEN AVE. STE. C, LAKELAND, GA, 31635", "county": "LANIER", "election": "11/04/2025 NOVEMBER 4, 2025 - MUNICIPAL GENERAL / SPECIAL ELECTION (PSC)", "lat": 31.042437, "lng": -83.090167, "name": "LANIER COUNTY BOARD OF ELECTIONS", "schedule": "10/20/2025 - 10/24/2025 8:00 AM - 5:00 PM ( Advanced Polling Location )\n10/25/2025 - 10/25/2025 9:00 AM - 5:00 PM ( Advanced Polling Location )\n10/27/2025 - 10/31/2025 8:00 AM - 5:00 PM ( Advanced Polling Location )\n10/20/2025 - 10/24/2025 8:00 AM - 5:00 PM ( Dropbox Polling Location )\n10/25/2025 - 10/25/2025 9:00 AM - 5:00 PM ( Dropbox Polling Location )\n10/27/2025 - 10/31/2025 8:00 AM - 5:00 PM ( Dropbox Polling Location )" }, "geometry": { "type": "Point", "coordinates": [ -83.090167, 31.042437 ] } }
]
}
