{
"type": "FeatureCollection",
"name": "MACON",
"crs": { "type": "name", "properties": { "name": "urn:ogc:def:crs:OGC:1.3:CRS84" } },
"features": [
{ "type": "Feature", "properties": { "address": "100 MACON STREET, OGLETHORPE, GA, 31068", "county": "MACON", "election": "11/04/2025 NOVEMBER 4, 2025 - MUNICIPAL GENERAL / SPECIAL ELECTION (PSC)", "lat": 32.29499, "lng": -84.05972, "name": "MACON COUNTY ANNEX", "schedule": "10/14/2025 - 10/27/2025 9:00 AM - 5:00 PM ( Advanced Polling Location )\n10/28/2025 - 10/31/2025 9:00 AM - 5:00 PM ( Advanced Polling Location )\n10/14/2025 - 10/27/2025 9:00 AM - 5:00 PM ( Dropbox Polling Location )\n10/28/2025 - 10/31/2025 9:00 AM - 5:00 PM ( Dropbox Polling Location )" }, "geometry": { "type": "Point", "coordinates": [ -84.05972, 32.29499 ] } }
]
}
