{
"type": "FeatureCollection",
"name": "TURNER",
"crs": { "type": "name", "properties": { "name": "urn:ogc:def:crs:OGC:1.3:CRS84" } },
"features": [
{ "type": "Feature", "properties": { "address": "1807 US HIGHWAY 41 N, SYCAMORE, GA, 31790", "county": "TURNER", "election": "11/04/2025 NOVEMBER 4, 2025 - MUNICIPAL GENERAL / SPECIAL ELECTION (PSC)", "lat": 31.683081, "lng": -83.641438, "name": "AMERICAN LEGION BUILDING", "schedule": "10/22/2025 - 10/22/2025 8:00 AM - 5:00 PM ( Advanced Polling Location )\n10/23/2025 - 10/23/2025 8:00 AM - 6:00 PM ( Advanced Polling Location )\n10/24/2025 - 10/24/2025 8:00 AM - 5:00 PM ( Advanced Polling Location )\n10/25/2025 - 10/25/2025 9:00 AM - 5:00 PM ( Advanced Polling Location )\n10/27/2025 - 10/27/2025 8:00 AM - 5:00 PM ( Advanced Polling Location )\n10/28/2025 - 10/28/2025 7:00 AM - 5:00 PM ( Advanced Polling Location )\n10/29/2025 - 10/29/2025 8:00 AM - 5:00 PM ( Advanced Polling Location )\n10/30/2025 - 10/30/2025 8:00 AM - 6:00 PM ( Advanced Polling Location )\n10/31/2025 - 10/31/2025 8:00 AM - 5:00 PM ( Advanced Polling Location )" }, "geometry": { "type": "Point", "coordinates": [ -83.641438, 31.683081 ] } }
]
}
