{
"type": "FeatureCollection",
"name": "WEBSTER",
"crs": { "type": "name", "properties": { "name": "urn:ogc:def:crs:OGC:1.3:CRS84" } },
"features": [
{ "type": "Feature", "properties": { "address": "40 CEMETERY ROAD, PRESTON, GA, 31824", "county": "WEBSTER", "election": "11/04/2025 NOVEMBER 4, 2025 - MUNICIPAL GENERAL / SPECIAL ELECTION (PSC)", "lat": 32.065537, "lng": -84.533366, "name": "WEBSTER COUNTY COMMISSIONER OFFICE", "schedule": "10/20/2025 - 10/25/2025 8:30 AM - 4:00 PM ( Advanced Polling Location )\n10/27/2025 - 10/31/2025 8:30 AM - 4:00 PM ( Advanced Polling Location )" }, "geometry": { "type": "Point", "coordinates": [ -84.533366, 32.065537 ] } }
]
}
