{
"type": "FeatureCollection",
"name": "WHITFIELD",
"crs": { "type": "name", "properties": { "name": "urn:ogc:def:crs:OGC:1.3:CRS84" } },
"features": [
{ "type": "Feature", "properties": { "address": "205 N SELVIDGE ST, DALTON, GA, 30720", "county": "WHITFIELD", "election": "11/04/2025 NOVEMBER 4, 2025 - MUNICIPAL GENERAL / SPECIAL ELECTION (PSC)", "lat": 34.772557, "lng": -84.971203, "name": "WHITFIELD COUNTY COURTHOUSE", "schedule": "10/31/2025 - 10/31/2025 8:00 AM - 5:00 PM ( Advanced Polling Location )\n10/20/2025 - 10/25/2025 8:00 AM - 5:00 PM ( Advanced Polling Location )\n10/25/2025 - 10/25/2025 9:00 AM - 5:00 PM ( Advanced Polling Location )\n10/27/2025 - 10/29/2025 8:00 AM - 5:00 PM ( Advanced Polling Location )\n10/30/2025 - 10/30/2025 8:00 AM - 5:00 PM ( Advanced Polling Location )\n10/31/2025 - 10/31/2025 8:00 AM - 5:00 PM ( Dropbox Polling Location )\n10/30/2025 - 10/30/2025 8:00 AM - 5:00 PM ( Dropbox Polling Location )\n10/25/2025 - 10/25/2025 9:00 AM - 5:00 PM ( Dropbox Polling Location )\n10/20/2025 - 10/24/2025 8:00 AM - 5:00 PM ( Dropbox Polling Location )\n10/27/2025 - 10/29/2025 8:00 AM - 5:00 PM ( Dropbox Polling Location )" }, "geometry": { "type": "Point", "coordinates": [ -84.971203, 34.772557 ] } }
]
}
